dpydialog/__init__.py
dpydialog/_config.py
dpydialog/_dialog.py
dpydialog/_formatter.py
dpydialog/_runner.py
dpydialog/constants.py
dpydialog/default_formatters.py
dpydialog/exceptions.py
dpydialog/types.py
dpy_dialog-0.0.1.dist-info/LICENSE
dpy_dialog-0.0.1.dist-info/METADATA
dpy_dialog-0.0.1.dist-info/WHEEL
dpy_dialog-0.0.1.dist-info/top_level.txt
dpy_dialog-0.0.1.dist-info/RECORD
