Metadata-Version: 2.1
Name: dpy-dialog
Version: 0.0.1
Summary: A dialog handler for discord.py to make multipart dialog through Discord easy
Author-email: "Tanner B. Corcoran" <tannerbcorcoran@gmail.com>
Project-URL: Homepage, https://github.com/tanrbobanr/dpy-dialog
Classifier: Programming Language :: Python :: 3
Classifier: License :: OSI Approved :: MIT License
Classifier: Operating System :: OS Independent
Requires-Python: >=3.11
License-File: LICENSE
Requires-Dist: discord.py (>=2.0.0)
